temperatura/__init__.py
temperatura/temperatura.py
temperatura-2.0.1.dist-info/LICENSE.txt
temperatura-2.0.1.dist-info/METADATA
temperatura-2.0.1.dist-info/WHEEL
temperatura-2.0.1.dist-info/top_level.txt
temperatura-2.0.1.dist-info/RECORD
