Metadata-Version: 2.1
Name: temperatura
Version: 2.0.1
Summary: Um simples conversor de temperatura (Celsius - Fahrenheit)
Home-page: https://github.com/lissandro1/li-simple-package-template
Author: Lissandro
License: MIT
License-File: LICENSE.txt
